{
  "project_info": {
    "project_number": "610191958703",
    "firebase_url": "https://debtdecoder-bcf2c-default-rtdb.firebaseio.com",
    "project_id": "debtdecoder-bcf2c",
    "storage_bucket": "debtdecoder-bcf2c.appspot.com"
  },
  "client": [
    {
      "client_info": {
        "mobilesdk_app_id": "1:610191958703:android:e7f52055bfbf5d8c53ea5a",
        "android_client_info": {
          "package_name": "com.example.debtdecoder"
        }
      },
      "oauth_client": [],
      "api_key": [
        {
          "current_key": "AIzaSyC-dhhPUCadIKsqtKN7ZBzzYuagn_Q4V8A"
        }
      ],
      "services": {
        "appinvite_service": {
          "other_platform_oauth_client": []
        }
      }
    },
    {
      "client_info": {
        "mobilesdk_app_id": "1:610191958703:android:fe17f720d15d047a53ea5a",
        "android_client_info": {
          "package_name": "com.example.expenses_and_budget_mobileassignment"
        }
      },
      "oauth_client": [],
      "api_key": [
        {
          "current_key": "AIzaSyC-dhhPUCadIKsqtKN7ZBzzYuagn_Q4V8A"
        }
      ],
      "services": {
        "appinvite_service": {
          "other_platform_oauth_client": []
        }
      }
    },
    {
      "client_info": {
        "mobilesdk_app_id": "1:610191958703:android:4d541bbe0802db7d53ea5a",
        "android_client_info": {
          "package_name": "my.edu.tarc.debtdecoder"
        }
      },
      "oauth_client": [],
      "api_key": [
        {
          "current_key": "AIzaSyC-dhhPUCadIKsqtKN7ZBzzYuagn_Q4V8A"
        }
      ],
      "services": {
        "appinvite_service": {
          "other_platform_oauth_client": []
        }
      }
    }
  ],
  "configuration_version": "1"
}